{"chunk_definitions":[{"row":14,"row_count":1,"visible":true,"expansion_state":0,"options":{"engine":"r","label":"setup","include":false},"document_id":"79FBCCAD","chunk_id":"csetup_chunk","chunk_label":"setup"},{"row":26,"row_count":1,"visible":true,"expansion_state":0,"options":{"engine":"r","label":"load packages","message":false,"warning":false,"paged.print":false},"document_id":"79FBCCAD","chunk_id":"cdbqry5vdehci","chunk_label":"load packages"},{"row":48,"row_count":1,"visible":true,"expansion_state":0,"options":{"engine":"r","label":"simulate Data"},"document_id":"79FBCCAD","chunk_id":"c289sh8g4whew","chunk_label":"simulate Data"},{"row":73,"row_count":1,"visible":true,"expansion_state":0,"options":{"engine":"r","label":"aggregate"},"document_id":"79FBCCAD","chunk_id":"cw28ez7tbm3i9","chunk_label":"aggregate"},{"row":88,"row_count":1,"visible":true,"expansion_state":0,"options":{"engine":"r","label":"lmmr rand int"},"document_id":"79FBCCAD","chunk_id":"cz0ugldvrp0ix","chunk_label":"lmmr rand int"},{"row":101,"row_count":1,"visible":true,"expansion_state":0,"options":{"engine":"r","label":"rand int test sig"},"document_id":"79FBCCAD","chunk_id":"cetdzax4d3sh4","chunk_label":"rand int test sig"},{"row":108,"row_count":1,"visible":true,"expansion_state":0,"options":{"engine":"r","label":"sim based test"},"document_id":"79FBCCAD","chunk_id":"cb1x920dg86ym","chunk_label":"sim based test"},{"row":124,"row_count":1,"visible":true,"expansion_state":0,"options":{"engine":"r","label":"maximal"},"document_id":"79FBCCAD","chunk_id":"cc9qi568wlemw","chunk_label":"maximal"},{"row":147,"row_count":1,"visible":true,"expansion_state":0,"options":{"engine":"r","label":"centering"},"document_id":"79FBCCAD","chunk_id":"cwb6gyki2qvx9","chunk_label":"centering"},{"row":161,"row_count":1,"visible":true,"expansion_state":0,"options":{"engine":"r","label":"model selection backward"},"document_id":"79FBCCAD","chunk_id":"ce98gofgg3e5n","chunk_label":"model selection backward"},{"row":204,"row_count":1,"visible":true,"expansion_state":0,"options":{"engine":"r","label":"categorical predictor between"},"document_id":"79FBCCAD","chunk_id":"c2orkcr0vicw8","chunk_label":"categorical predictor between"},{"row":229,"row_count":1,"visible":true,"expansion_state":0,"options":{"engine":"r","label":"setting contrasts"},"document_id":"79FBCCAD","chunk_id":"crbpppra5prwf","chunk_label":"setting contrasts"},{"row":255,"row_count":1,"visible":true,"expansion_state":0,"options":{"engine":"r","label":"continuous predictor between"},"document_id":"79FBCCAD","chunk_id":"cygfxj0glfgdi","chunk_label":"continuous predictor between"},{"row":285,"row_count":1,"visible":true,"expansion_state":0,"options":{"engine":"r","label":"categorical predictor within ez"},"document_id":"79FBCCAD","chunk_id":"cge4kcdk5u1gv","chunk_label":"categorical predictor within ez"},{"row":334,"row_count":1,"visible":true,"expansion_state":0,"options":{"engine":"r","label":"categorical predictor within mixed-effects"},"document_id":"79FBCCAD","chunk_id":"c4zg8n7hs6ewk","chunk_label":"categorical predictor within mixed-effects"}],"doc_write_time":1615541449,"working_dir":null,"default_chunk_options":{"echo":true}}